LICENSE
README.md
setup.py
servyou_log.egg-info/PKG-INFO
servyou_log.egg-info/SOURCES.txt
servyou_log.egg-info/dependency_links.txt
servyou_log.egg-info/requires.txt
servyou_log.egg-info/top_level.txt
seryou_log/__init__.py
seryou_log/file_lock.py
seryou_log/handlers.py
seryou_log/load_log_config.py
seryou_log/log_config.py
seryou_log/pring_tools.py
seryou_log/servyou_log.py