Metadata-Version: 2.1
Name: servyou-log
Version: 2.6
Summary: 日志工具类
Home-page: UNKNOWN
Author: PubDesktop
License: UNKNOWN
Platform: all
Classifier: Programming Language :: Python :: 3
Classifier: License :: OSI Approved :: MIT License
Classifier: Operating System :: OS Independent
Requires-Python: >2
License-File: LICENSE
